audiosr/__init__.py
audiosr/__main__.py
audiosr/lowpass.py
audiosr/pipeline.py
audiosr/utils.py
audiosr/clap/__init__.py
audiosr/clap/open_clip/__init__.py
audiosr/clap/open_clip/bpe_simple_vocab_16e6.txt.gz
audiosr/clap/open_clip/factory.py
audiosr/clap/open_clip/feature_fusion.py
audiosr/clap/open_clip/htsat.py
audiosr/clap/open_clip/loss.py
audiosr/clap/open_clip/model.py
audiosr/clap/open_clip/openai.py
audiosr/clap/open_clip/pann_model.py
audiosr/clap/open_clip/pretrained.py
audiosr/clap/open_clip/timm_model.py
audiosr/clap/open_clip/tokenizer.py
audiosr/clap/open_clip/transform.py
audiosr/clap/open_clip/utils.py
audiosr/clap/open_clip/model_configs/HTSAT-base.json
audiosr/clap/open_clip/model_configs/HTSAT-large.json
audiosr/clap/open_clip/model_configs/HTSAT-tiny-win-1536.json
audiosr/clap/open_clip/model_configs/HTSAT-tiny.json
audiosr/clap/open_clip/model_configs/PANN-10.json
audiosr/clap/open_clip/model_configs/PANN-14-fmax-18k.json
audiosr/clap/open_clip/model_configs/PANN-14-fmax-8k-20s.json
audiosr/clap/open_clip/model_configs/PANN-14-tiny-transformer.json
audiosr/clap/open_clip/model_configs/PANN-14-win-1536.json
audiosr/clap/open_clip/model_configs/PANN-14.json
audiosr/clap/open_clip/model_configs/PANN-6.json
audiosr/clap/open_clip/model_configs/RN101-quickgelu.json
audiosr/clap/open_clip/model_configs/RN101.json
audiosr/clap/open_clip/model_configs/RN50-quickgelu.json
audiosr/clap/open_clip/model_configs/RN50.json
audiosr/clap/open_clip/model_configs/RN50x16.json
audiosr/clap/open_clip/model_configs/RN50x4.json
audiosr/clap/open_clip/model_configs/ViT-B-16.json
audiosr/clap/open_clip/model_configs/ViT-B-32-quickgelu.json
audiosr/clap/open_clip/model_configs/ViT-B-32.json
audiosr/clap/open_clip/model_configs/ViT-L-14.json
audiosr/clap/training/__init__.py
audiosr/clap/training/audioset_textmap.npy
audiosr/clap/training/bpe_simple_vocab_16e6.txt.gz
audiosr/clap/training/data.py
audiosr/clap/training/params.py
audiosr/hifigan/__init__.py
audiosr-0.0.7.dist-info/LICENSE
audiosr-0.0.7.dist-info/METADATA
audiosr-0.0.7.dist-info/WHEEL
audiosr-0.0.7.dist-info/top_level.txt
audiosr-0.0.7.dist-info/RECORD
