Metadata-Version: 2.1
Name: audiosr
Version: 0.0.7
Summary: This package is written for text-to-audio/music generation.
Home-page: https://github.com/haoheliu/audiosr
Author: Haohe Liu
Author-email: haoheliu@gmail.com
License: MIT
Platform: UNKNOWN
Classifier: License :: OSI Approved :: MIT License
Classifier: Programming Language :: Python
Classifier: Programming Language :: Python :: 3
Classifier: Programming Language :: Python :: 3.7
Classifier: Programming Language :: Python :: Implementation :: CPython
Classifier: Programming Language :: Python :: Implementation :: PyPy
Requires-Python: >=3.7.0
License-File: LICENSE
